README.rst
mubi.py
setup.py
mubi.egg-info/PKG-INFO
mubi.egg-info/SOURCES.txt
mubi.egg-info/dependency_links.txt
mubi.egg-info/not-zip-safe
mubi.egg-info/requires.txt
mubi.egg-info/top_level.txt