Metadata-Version: 1.1
Name: mubi
Version: 0.1.0
Summary: Helps you log in to mubi.com
Home-page: https://github.com/mstolyarchuk/mubi.py
Author: Maxim Stolyarchuk
Author-email: maxim.stolyarchuk@gmail.com
License: UNKNOWN
Platform: UNKNOWN
Classifier: Intended Audience :: Developers
Classifier: Operating System :: OS Independent
Classifier: Topic :: Software Development :: Libraries :: Python Modules
